wiley_tdm/__init__.py
wiley_tdm/doi_utils.py
wiley_tdm/download_result.py
wiley_tdm/download_status.py
wiley_tdm/file_utils.py
wiley_tdm/ip_utils.py
wiley_tdm/tdm_client.py
wiley_tdm/tdm_reporting.py
wiley_tdm/types.py
wiley_tdm-1.0.0.dist-info/METADATA
wiley_tdm-1.0.0.dist-info/WHEEL
wiley_tdm-1.0.0.dist-info/licenses/LICENSE
wiley_tdm-1.0.0.dist-info/RECORD
