Metadata-Version: 2.4
Name: wiley-tdm
Version: 1.0.0
Summary: Client for downloading Article PDFs from Wiley's TDM API
Author-email: Wiley Labs <tdm@wiley.com>
License: MIT License
License-File: LICENSE
Keywords: api,client,data-mining,doi,pdf,sdk,tdm,text-mining,wiley
Classifier: Development Status :: 4 - Beta
Classifier: Intended Audience :: Science/Research
Classifier: License :: OSI Approved :: MIT License
Classifier: Programming Language :: Python :: 3.9
Classifier: Topic :: Scientific/Engineering :: Information Analysis
Requires-Python: >=3.9
Requires-Dist: requests>=2.32.0
Provides-Extra: build
Requires-Dist: build>=1.0.3; extra == 'build'
Requires-Dist: twine>=6.1.0; extra == 'build'
Provides-Extra: dev
Requires-Dist: black>=25.1.0; extra == 'dev'
Requires-Dist: build>=1.0.3; extra == 'dev'
Requires-Dist: isort>=6.0.1; extra == 'dev'
Requires-Dist: pylint>=3.3.1; extra == 'dev'
Requires-Dist: pytest-cov>=6.1.1; extra == 'dev'
Requires-Dist: pytest>=8.3.5; extra == 'dev'
Requires-Dist: twine>=6.1.0; extra == 'dev'
Provides-Extra: lint
Requires-Dist: black>=25.1.0; extra == 'lint'
Requires-Dist: isort>=6.0.1; extra == 'lint'
Requires-Dist: pylint>=3.3.1; extra == 'lint'
Requires-Dist: pytest>=8.3.5; extra == 'lint'
Provides-Extra: test
Requires-Dist: pytest-cov>=6.1.1; extra == 'test'
Requires-Dist: pytest>=8.3.5; extra == 'test'
